nvidia/__init__.py
nvidia/npp/__init__.py
nvidia/npp/include/__init__.py
nvidia/npp/include/npp.h
nvidia/npp/include/nppcore.h
nvidia/npp/include/nppdefs.h
nvidia/npp/include/nppi.h
nvidia/npp/include/nppi_arithmetic_and_logical_operations.h
nvidia/npp/include/nppi_color_conversion.h
nvidia/npp/include/nppi_data_exchange_and_initialization.h
nvidia/npp/include/nppi_filtering_functions.h
nvidia/npp/include/nppi_geometry_transforms.h
nvidia/npp/include/nppi_linear_transforms.h
nvidia/npp/include/nppi_morphological_operations.h
nvidia/npp/include/nppi_statistics_functions.h
nvidia/npp/include/nppi_support_functions.h
nvidia/npp/include/nppi_threshold_and_compare_operations.h
nvidia/npp/include/npps.h
nvidia/npp/include/npps_arithmetic_and_logical_operations.h
nvidia/npp/include/npps_conversion_functions.h
nvidia/npp/include/npps_filtering_functions.h
nvidia/npp/include/npps_initialization.h
nvidia/npp/include/npps_statistics_functions.h
nvidia/npp/include/npps_support_functions.h
nvidia/npp/lib/__init__.py
nvidia/npp/lib/libnppc.so.11
nvidia/npp/lib/libnppial.so.11
nvidia/npp/lib/libnppicc.so.11
nvidia/npp/lib/libnppidei.so.11
nvidia/npp/lib/libnppif.so.11
nvidia/npp/lib/libnppig.so.11
nvidia/npp/lib/libnppim.so.11
nvidia/npp/lib/libnppist.so.11
nvidia/npp/lib/libnppisu.so.11
nvidia/npp/lib/libnppitc.so.11
nvidia/npp/lib/libnpps.so.11
nvidia_npp_cu11-11.8.0.86.dist-info/License.txt
nvidia_npp_cu11-11.8.0.86.dist-info/METADATA
nvidia_npp_cu11-11.8.0.86.dist-info/WHEEL
nvidia_npp_cu11-11.8.0.86.dist-info/top_level.txt
nvidia_npp_cu11-11.8.0.86.dist-info/RECORD
